MANIFEST.in
fungus_01_intro.py
fungus_audio_scene.py
fungus_core.py
fungus_game.py
fungus_scene.py
fungus_swarm.py
setup.py
Fungus.egg-info/PKG-INFO
Fungus.egg-info/SOURCES.txt
Fungus.egg-info/dependency_links.txt
Fungus.egg-info/top_level.txt
audio/__init__.py
graphics/__init__.py
lib/__init__.py
pyglet/__init__.py
pyglet/clock.py
pyglet/com.py
pyglet/event.py
pyglet/info.py
pyglet/lib.py
pyglet/resource.py
pyglet/sprite.py
pyglet/app/__init__.py
pyglet/app/carbon.py
pyglet/app/win32.py
pyglet/app/xlib.py
pyglet/font/__init__.py
pyglet/font/base.py
pyglet/font/carbon.py
pyglet/font/freetype.py
pyglet/font/freetype_lib.py
pyglet/font/ttf.py
pyglet/font/win32.py
pyglet/gl/__init__.py
pyglet/gl/agl.py
pyglet/gl/gl.py
pyglet/gl/gl_info.py
pyglet/gl/glext_arb.py
pyglet/gl/glext_missing.py
pyglet/gl/glext_nv.py
pyglet/gl/glu.py
pyglet/gl/glu_info.py
pyglet/gl/glx.py
pyglet/gl/glx_info.py
pyglet/gl/glxext_arb.py
pyglet/gl/glxext_mesa.py
pyglet/gl/glxext_nv.py
pyglet/gl/lib.py
pyglet/gl/lib_agl.py
pyglet/gl/lib_glx.py
pyglet/gl/lib_wgl.py
pyglet/gl/wgl.py
pyglet/gl/wgl_info.py
pyglet/gl/wglext_arb.py
pyglet/gl/wglext_nv.py
pyglet/graphics/__init__.py
pyglet/graphics/allocation.py
pyglet/graphics/vertexattribute.py
pyglet/graphics/vertexbuffer.py
pyglet/graphics/vertexdomain.py
pyglet/image/__init__.py
pyglet/image/atlas.py
pyglet/image/codecs/__init__.py
pyglet/image/codecs/bmp.py
pyglet/image/codecs/dds.py
pyglet/image/codecs/gdiplus.py
pyglet/image/codecs/gdkpixbuf2.py
pyglet/image/codecs/gif.py
pyglet/image/codecs/pil.py
pyglet/image/codecs/png.py
pyglet/image/codecs/pypng.py
pyglet/image/codecs/quicktime.py
pyglet/image/codecs/s3tc.py
pyglet/media/__init__.py
pyglet/media/avbin.py
pyglet/media/procedural.py
pyglet/media/riff.py
pyglet/media/drivers/__init__.py
pyglet/media/drivers/silent.py
pyglet/media/drivers/alsa/__init__.py
pyglet/media/drivers/alsa/asound.py
pyglet/media/drivers/directsound/__init__.py
pyglet/media/drivers/directsound/lib_dsound.py
pyglet/media/drivers/openal/__init__.py
pyglet/media/drivers/openal/lib_alc.py
pyglet/media/drivers/openal/lib_openal.py
