Metadata-Version: 1.1
Name: Fungus
Version: 0.1.1
Summary: ['A simple scene based game engine building on pyglet.']
Home-page: http://freehg.org/u/ArneBab/fungus
Author: Phillip Schoenherr and Arne Babenhauserheide
Author-email: arne_bab@web.de
License: GNU GPL-3 or later
Keywords: game engine,pyglet
Platform: any
Classifier: License :: OSI Approved :: GNU General Public License (GPL)
Classifier: Programming Language :: Python
Classifier: Operating System :: OS Independent
Classifier: Intended Audience :: Developers
Classifier: Intended Audience :: End Users/Desktop
Classifier: Environment :: Console
Classifier: Development Status :: 3 - Alpha
Classifier: Topic :: Games/Entertainment
Requires: pyglet
